aliyunsdkquotas/__init__.py
aliyunsdkquotas/endpoint.py
aliyunsdkquotas/request/__init__.py
aliyunsdkquotas/request/v20200510/CreateQuotaAlarmRequest.py
aliyunsdkquotas/request/v20200510/CreateQuotaApplicationRequest.py
aliyunsdkquotas/request/v20200510/CreateQuotaApplicationsForTemplateRequest.py
aliyunsdkquotas/request/v20200510/CreateTemplateQuotaItemRequest.py
aliyunsdkquotas/request/v20200510/DeleteQuotaAlarmRequest.py
aliyunsdkquotas/request/v20200510/DeleteTemplateQuotaItemRequest.py
aliyunsdkquotas/request/v20200510/GetProductQuotaDimensionRequest.py
aliyunsdkquotas/request/v20200510/GetProductQuotaRequest.py
aliyunsdkquotas/request/v20200510/GetQuotaAlarmRequest.py
aliyunsdkquotas/request/v20200510/GetQuotaApplicationApprovalRequest.py
aliyunsdkquotas/request/v20200510/GetQuotaApplicationRequest.py
aliyunsdkquotas/request/v20200510/GetQuotaTemplateServiceStatusRequest.py
aliyunsdkquotas/request/v20200510/ListAlarmHistoriesRequest.py
aliyunsdkquotas/request/v20200510/ListDependentQuotasRequest.py
aliyunsdkquotas/request/v20200510/ListProductDimensionGroupsRequest.py
aliyunsdkquotas/request/v20200510/ListProductQuotaDimensionsRequest.py
aliyunsdkquotas/request/v20200510/ListProductQuotasRequest.py
aliyunsdkquotas/request/v20200510/ListProductsRequest.py
aliyunsdkquotas/request/v20200510/ListQuotaAlarmsRequest.py
aliyunsdkquotas/request/v20200510/ListQuotaApplicationTemplatesRequest.py
aliyunsdkquotas/request/v20200510/ListQuotaApplicationsDetailForTemplateRequest.py
aliyunsdkquotas/request/v20200510/ListQuotaApplicationsForTemplateRequest.py
aliyunsdkquotas/request/v20200510/ListQuotaApplicationsRequest.py
aliyunsdkquotas/request/v20200510/ModifyQuotaTemplateServiceStatusRequest.py
aliyunsdkquotas/request/v20200510/ModifyTemplateQuotaItemRequest.py
aliyunsdkquotas/request/v20200510/RemindQuotaApplicationApprovalRequest.py
aliyunsdkquotas/request/v20200510/UpdateQuotaAlarmRequest.py
aliyunsdkquotas/request/v20200510/__init__.py
aliyun_python_sdk_quotas-1.0.4.dist-info/LICENSE
aliyun_python_sdk_quotas-1.0.4.dist-info/METADATA
aliyun_python_sdk_quotas-1.0.4.dist-info/WHEEL
aliyun_python_sdk_quotas-1.0.4.dist-info/top_level.txt
aliyun_python_sdk_quotas-1.0.4.dist-info/RECORD
